{
  "name": "Hard Leather Body",
  "description": "A hardened leather body armor with reinforced construction and improved durability",
  "type": "armor",
  "subtype": "body",
  "style": "realistic",
  "metadata": {
    "tier": "hard_leather",
    "level": 3,
    "gameId": "hard_leather_body",
    "rarity": "common",
    "defenseLevel": 3,
    "slot": "body"
  },
  "id": "hard-leather-body",
  "analysisResult": {
    "slot": "body",
    "attachmentPoint": {
      "x": 0,
      "y": 0,
      "z": 0
    },
    "rotation": {
      "x": 0,
      "y": 0,
      "z": 0,
      "w": 1
    },
    "scale": {
      "x": 1,
      "y": 1,
      "z": 1
    }
  },
  "generatedAt": "2025-07-18T08:44:44.635Z",
  "modelPath": "/Users/shawwalters/hyperscape/packages/generation/gdd-assets/hard-leather-body/Hard Leather Body.glb"
}